plugcli/__init__.py
plugcli/_installed_version.py
plugcli/cli.py
plugcli/params.py
plugcli/plugin_management.py
plugcli/version.py
plugcli/tests/__init__.py
plugcli/tests/test_cli.py
plugcli/tests/test_params.py
plugcli/tests/test_plugin_management.py
plugcli/tests/plugin_examples/__init__.py
plugcli/tests/plugin_examples/exampleA.py
plugcli/tests/plugin_examples/exampleB.py
plugcli-0.2.1.dist-info/licenses/LICENSE
plugcli-0.2.1.dist-info/METADATA
plugcli-0.2.1.dist-info/WHEEL
plugcli-0.2.1.dist-info/top_level.txt
plugcli-0.2.1.dist-info/RECORD
