Metadata-Version: 2.4
Name: plugcli
Version: 0.2.1
Summary: Plugin based CLI framework built on click
Home-page: https://github.com/dwhswenson/plugcli
Author: David W.H. Swenson
Author-email: dwhs@hyperblazer.net
License: MIT
Classifier: License :: OSI Approved :: MIT License
License-File: LICENSE
Requires-Dist: click
Dynamic: license-file
